sopel_tld/__init__.py
sopel_tld/plugin.py
sopel_tld-0.1.3.dist-info/licenses/COPYING
sopel_tld-0.1.3.dist-info/METADATA
sopel_tld-0.1.3.dist-info/WHEEL
sopel_tld-0.1.3.dist-info/entry_points.txt
sopel_tld-0.1.3.dist-info/top_level.txt
sopel_tld-0.1.3.dist-info/RECORD
