Metadata-Version: 2.4
Name: sopel-tld
Version: 0.1.3
Summary: Top-level domain (TLD) info plugin for Sopel IRC bots.
Author: Michael Yanovich
Author-email: dgw <dgw@technobabbl.es>
Maintainer-email: dgw <dgw@technobabbl.es>
License-Expression: EFL-2.0
Project-URL: Homepage, https://github.com/sopel-irc/sopel-tld
Project-URL: Bug Tracker, https://github.com/sopel-irc/sopel-tld/issues
Keywords: sopel,plugin,bot,irc
Platform: Linux x86, x86-64
Classifier: Intended Audience :: Developers
Classifier: Intended Audience :: System Administrators
Classifier: Topic :: Communications :: Chat :: Internet Relay Chat
Requires-Python: <4,>=3.8
License-File: COPYING
Requires-Dist: sopel>=8.0
Requires-Dist: packaging
Requires-Dist: requests
Requires-Dist: pytz
Dynamic: license-file
